{
  "nodes": [
    {
      "name": "Global Liquidity",
      "itemStyle": {
        "color": "#f8fafc"
      },
      "depth": 0
    },
    {
      "name": "Equities",
      "itemStyle": {
        "color": "#10b981"
      },
      "depth": 1
    },
    {
      "name": "USA",
      "itemStyle": {
        "color": "#10b981"
      },
      "depth": 2
    },
    {
      "name": "Mega-Cap Tech",
      "itemStyle": {
        "color": "#10b981"
      },
      "depth": 3
    },
    {
      "name": "AMD",
      "itemStyle": {
        "color": "#10b981"
      },
      "depth": 4
    },
    {
      "name": "AAPL",
      "itemStyle": {
        "color": "#10b981"
      },
      "depth": 4
    },
    {
      "name": "QCOM",
      "itemStyle": {
        "color": "#10b981"
      },
      "depth": 4
    },
    {
      "name": "NVDA",
      "itemStyle": {
        "color": "#10b981"
      },
      "depth": 4
    },
    {
      "name": "GOOGL",
      "itemStyle": {
        "color": "#10b981"
      },
      "depth": 4
    },
    {
      "name": "MSFT",
      "itemStyle": {
        "color": "#ef4444"
      },
      "depth": 4
    },
    {
      "name": "AVGO",
      "itemStyle": {
        "color": "#10b981"
      },
      "depth": 4
    },
    {
      "name": "CRM",
      "itemStyle": {
        "color": "#ef4444"
      },
      "depth": 4
    },
    {
      "name": "META",
      "itemStyle": {
        "color": "#ef4444"
      },
      "depth": 4
    },
    {
      "name": "AI & Cloud Growth",
      "itemStyle": {
        "color": "#10b981"
      },
      "depth": 3
    },
    {
      "name": "MU",
      "itemStyle": {
        "color": "#10b981"
      },
      "depth": 4
    },
    {
      "name": "INTC",
      "itemStyle": {
        "color": "#10b981"
      },
      "depth": 4
    },
    {
      "name": "ARM",
      "itemStyle": {
        "color": "#10b981"
      },
      "depth": 4
    },
    {
      "name": "PANW",
      "itemStyle": {
        "color": "#10b981"
      },
      "depth": 4
    },
    {
      "name": "SNOW",
      "itemStyle": {
        "color": "#10b981"
      },
      "depth": 4
    },
    {
      "name": "DDOG",
      "itemStyle": {
        "color": "#10b981"
      },
      "depth": 4
    },
    {
      "name": "TSM",
      "itemStyle": {
        "color": "#10b981"
      },
      "depth": 4
    },
    {
      "name": "CRWD",
      "itemStyle": {
        "color": "#10b981"
      },
      "depth": 4
    },
    {
      "name": "ASML",
      "itemStyle": {
        "color": "#10b981"
      },
      "depth": 4
    },
    {
      "name": "NET",
      "itemStyle": {
        "color": "#10b981"
      },
      "depth": 4
    },
    {
      "name": "MDB",
      "itemStyle": {
        "color": "#10b981"
      },
      "depth": 4
    },
    {
      "name": "PLTR",
      "itemStyle": {
        "color": "#ef4444"
      },
      "depth": 4
    },
    {
      "name": "ZS",
      "itemStyle": {
        "color": "#10b981"
      },
      "depth": 4
    },
    {
      "name": "U",
      "itemStyle": {
        "color": "#10b981"
      },
      "depth": 4
    },
    {
      "name": "SOFI",
      "itemStyle": {
        "color": "#10b981"
      },
      "depth": 4
    },
    {
      "name": "SMCI",
      "itemStyle": {
        "color": "#10b981"
      },
      "depth": 4
    },
    {
      "name": "AI",
      "itemStyle": {
        "color": "#10b981"
      },
      "depth": 4
    },
    {
      "name": "Financials",
      "itemStyle": {
        "color": "#10b981"
      },
      "depth": 3
    },
    {
      "name": "GS",
      "itemStyle": {
        "color": "#10b981"
      },
      "depth": 4
    },
    {
      "name": "V",
      "itemStyle": {
        "color": "#10b981"
      },
      "depth": 4
    },
    {
      "name": "JPM",
      "itemStyle": {
        "color": "#10b981"
      },
      "depth": 4
    },
    {
      "name": "BAC",
      "itemStyle": {
        "color": "#10b981"
      },
      "depth": 4
    },
    {
      "name": "MA",
      "itemStyle": {
        "color": "#10b981"
      },
      "depth": 4
    },
    {
      "name": "WFC",
      "itemStyle": {
        "color": "#10b981"
      },
      "depth": 4
    },
    {
      "name": "BLK",
      "itemStyle": {
        "color": "#ef4444"
      },
      "depth": 4
    },
    {
      "name": "BX",
      "itemStyle": {
        "color": "#ef4444"
      },
      "depth": 4
    },
    {
      "name": "Healthcare",
      "itemStyle": {
        "color": "#10b981"
      },
      "depth": 3
    },
    {
      "name": "UNH",
      "itemStyle": {
        "color": "#10b981"
      },
      "depth": 4
    },
    {
      "name": "LLY",
      "itemStyle": {
        "color": "#10b981"
      },
      "depth": 4
    },
    {
      "name": "ABBV",
      "itemStyle": {
        "color": "#10b981"
      },
      "depth": 4
    },
    {
      "name": "PFE",
      "itemStyle": {
        "color": "#ef4444"
      },
      "depth": 4
    },
    {
      "name": "JNJ",
      "itemStyle": {
        "color": "#10b981"
      },
      "depth": 4
    },
    {
      "name": "MRK",
      "itemStyle": {
        "color": "#10b981"
      },
      "depth": 4
    },
    {
      "name": "Industrials",
      "itemStyle": {
        "color": "#10b981"
      },
      "depth": 3
    },
    {
      "name": "CAT",
      "itemStyle": {
        "color": "#10b981"
      },
      "depth": 4
    },
    {
      "name": "GE",
      "itemStyle": {
        "color": "#10b981"
      },
      "depth": 4
    },
    {
      "name": "UNP",
      "itemStyle": {
        "color": "#10b981"
      },
      "depth": 4
    },
    {
      "name": "LMT",
      "itemStyle": {
        "color": "#ef4444"
      },
      "depth": 4
    },
    {
      "name": "BA",
      "itemStyle": {
        "color": "#ef4444"
      },
      "depth": 4
    },
    {
      "name": "Consumer",
      "itemStyle": {
        "color": "#ef4444"
      },
      "depth": 3
    },
    {
      "name": "TSLA",
      "itemStyle": {
        "color": "#10b981"
      },
      "depth": 4
    },
    {
      "name": "AMZN",
      "itemStyle": {
        "color": "#ef4444"
      },
      "depth": 4
    },
    {
      "name": "MCD",
      "itemStyle": {
        "color": "#ef4444"
      },
      "depth": 4
    },
    {
      "name": "SBUX",
      "itemStyle": {
        "color": "#10b981"
      },
      "depth": 4
    },
    {
      "name": "NKE",
      "itemStyle": {
        "color": "#ef4444"
      },
      "depth": 4
    },
    {
      "name": "HD",
      "itemStyle": {
        "color": "#ef4444"
      },
      "depth": 4
    },
    {
      "name": "Emerging Markets",
      "itemStyle": {
        "color": "#10b981"
      },
      "depth": 2
    },
    {
      "name": "Asia-Pacific",
      "itemStyle": {
        "color": "#10b981"
      },
      "depth": 2
    },
    {
      "name": "Europe",
      "itemStyle": {
        "color": "#10b981"
      },
      "depth": 2
    },
    {
      "name": "Crypto",
      "itemStyle": {
        "color": "#ef4444"
      },
      "depth": 1
    },
    {
      "name": "MicroStrategy",
      "itemStyle": {
        "color": "#ef4444"
      },
      "depth": 2
    },
    {
      "name": "Bitcoin",
      "itemStyle": {
        "color": "#ef4444"
      },
      "depth": 2
    },
    {
      "name": "Coinbase",
      "itemStyle": {
        "color": "#ef4444"
      },
      "depth": 2
    },
    {
      "name": "Ethereum",
      "itemStyle": {
        "color": "#ef4444"
      },
      "depth": 2
    },
    {
      "name": "Fixed Income",
      "itemStyle": {
        "color": "#ef4444"
      },
      "depth": 1
    },
    {
      "name": "Real Estate",
      "itemStyle": {
        "color": "#10b981"
      },
      "depth": 1
    },
    {
      "name": "Commodities",
      "itemStyle": {
        "color": "#ef4444"
      },
      "depth": 1
    },
    {
      "name": "Gold",
      "itemStyle": {
        "color": "#ef4444"
      },
      "depth": 2
    },
    {
      "name": "Silver",
      "itemStyle": {
        "color": "#ef4444"
      },
      "depth": 2
    },
    {
      "name": "Crude Oil",
      "itemStyle": {
        "color": "#ef4444"
      },
      "depth": 2
    },
    {
      "name": "Copper",
      "itemStyle": {
        "color": "#10b981"
      },
      "depth": 2
    }
  ],
  "links": [
    {
      "source": "Global Liquidity",
      "target": "Equities",
      "value": 16297.52,
      "net_flow_dollars": 162975225269.41965,
      "market_cap_delta": 51294814467.45246,
      "lineStyle": {
        "color": "#10b981",
        "opacity": 0.35
      }
    },
    {
      "source": "Equities",
      "target": "USA",
      "value": 16297.52,
      "net_flow_dollars": 162975225269.41965,
      "market_cap_delta": 51294814467.45246,
      "lineStyle": {
        "color": "#10b981",
        "opacity": 0.35
      }
    },
    {
      "source": "USA",
      "target": "Mega-Cap Tech",
      "value": 2924.37,
      "net_flow_dollars": 29243731117.379845,
      "market_cap_delta": 9256704403.701172,
      "lineStyle": {
        "color": "#10b981",
        "opacity": 0.35
      }
    },
    {
      "source": "Mega-Cap Tech",
      "target": "AMD",
      "value": 101328.22,
      "net_flow_dollars": 1013282234491.0498,
      "market_cap_delta": 482657801086.8758,
      "lineStyle": {
        "color": "#10b981",
        "opacity": 0.35
      }
    },
    {
      "source": "Mega-Cap Tech",
      "target": "AAPL",
      "value": 14812.59,
      "net_flow_dollars": 148125853446.16354,
      "market_cap_delta": 810154413528.7893,
      "lineStyle": {
        "color": "#10b981",
        "opacity": 0.35
      }
    },
    {
      "source": "Mega-Cap Tech",
      "target": "QCOM",
      "value": 8051.44,
      "net_flow_dollars": 80514389516.32689,
      "market_cap_delta": 50565652573.24218,
      "lineStyle": {
        "color": "#10b981",
        "opacity": 0.35
      }
    },
    {
      "source": "Mega-Cap Tech",
      "target": "NVDA",
      "value": 7767.18,
      "net_flow_dollars": 77671760296.595,
      "market_cap_delta": 223821258322.75415,
      "lineStyle": {
        "color": "#10b981",
        "opacity": 0.35
      }
    },
    {
      "source": "Mega-Cap Tech",
      "target": "GOOGL",
      "value": 3504.58,
      "net_flow_dollars": 35045822170.528656,
      "market_cap_delta": 129194727523.46742,
      "lineStyle": {
        "color": "#10b981",
        "opacity": 0.35
      }
    },
    {
      "source": "Mega-Cap Tech",
      "target": "MSFT",
      "value": 1770.98,
      "net_flow_dollars": -17709839931.915886,
      "market_cap_delta": -69455791939.09244,
      "lineStyle": {
        "color": "#ef4444",
        "opacity": 0.35
      }
    },
    {
      "source": "Mega-Cap Tech",
      "target": "AVGO",
      "value": 1330.89,
      "net_flow_dollars": 13308901476.176575,
      "market_cap_delta": 49669143074.71314,
      "lineStyle": {
        "color": "#10b981",
        "opacity": 0.35
      }
    },
    {
      "source": "Mega-Cap Tech",
      "target": "CRM",
      "value": 360.34,
      "net_flow_dollars": -3603443163.2992835,
      "market_cap_delta": -4127756500.8544936,
      "lineStyle": {
        "color": "#ef4444",
        "opacity": 0.35
      }
    },
    {
      "source": "Mega-Cap Tech",
      "target": "META",
      "value": 348.09,
      "net_flow_dollars": -3480925554.2544813,
      "market_cap_delta": -9223439722.554834,
      "lineStyle": {
        "color": "#ef4444",
        "opacity": 0.35
      }
    },
    {
      "source": "USA",
      "target": "AI & Cloud Growth",
      "value": 1789.2,
      "net_flow_dollars": 17892036084.01384,
      "market_cap_delta": 165500015.258789,
      "lineStyle": {
        "color": "#10b981",
        "opacity": 0.35
      }
    },
    {
      "source": "AI & Cloud Growth",
      "target": "MU",
      "value": 246042.57,
      "net_flow_dollars": 2460425728996.444,
      "market_cap_delta": 556333424731.46,
      "lineStyle": {
        "color": "#10b981",
        "opacity": 0.35
      }
    },
    {
      "source": "AI & Cloud Growth",
      "target": "INTC",
      "value": 49887.26,
      "net_flow_dollars": 498872563801.9852,
      "market_cap_delta": 202145713864.74606,
      "lineStyle": {
        "color": "#10b981",
        "opacity": 0.35
      }
    },
    {
      "source": "AI & Cloud Growth",
      "target": "ARM",
      "value": 13123.2,
      "net_flow_dollars": 131231976728.92389,
      "market_cap_delta": 130059940174.74338,
      "lineStyle": {
        "color": "#10b981",
        "opacity": 0.35
      }
    },
    {
      "source": "AI & Cloud Growth",
      "target": "PANW",
      "value": 11211.95,
      "net_flow_dollars": 112119492643.07436,
      "market_cap_delta": 149365038061.5234,
      "lineStyle": {
        "color": "#10b981",
        "opacity": 0.35
      }
    },
    {
      "source": "AI & Cloud Growth",
      "target": "SNOW",
      "value": 8780.52,
      "net_flow_dollars": 87805214248.12848,
      "market_cap_delta": 47198251192.13867,
      "lineStyle": {
        "color": "#10b981",
        "opacity": 0.35
      }
    },
    {
      "source": "AI & Cloud Growth",
      "target": "DDOG",
      "value": 8204.62,
      "net_flow_dollars": 82046215121.55977,
      "market_cap_delta": 51269732487.29095,
      "lineStyle": {
        "color": "#10b981",
        "opacity": 0.35
      }
    },
    {
      "source": "AI & Cloud Growth",
      "target": "TSM",
      "value": 3548.69,
      "net_flow_dollars": 35486942962.456245,
      "market_cap_delta": 217935657019.69516,
      "lineStyle": {
        "color": "#10b981",
        "opacity": 0.35
      }
    },
    {
      "source": "AI & Cloud Growth",
      "target": "CRWD",
      "value": 3080.27,
      "net_flow_dollars": 30802701878.31069,
      "market_cap_delta": 103799311998.65543,
      "lineStyle": {
        "color": "#10b981",
        "opacity": 0.35
      }
    },
    {
      "source": "AI & Cloud Growth",
      "target": "ASML",
      "value": 2798.92,
      "net_flow_dollars": 27989206852.717754,
      "market_cap_delta": 93625647890.26686,
      "lineStyle": {
        "color": "#10b981",
        "opacity": 0.35
      }
    },
    {
      "source": "AI & Cloud Growth",
      "target": "NET",
      "value": 2731.29,
      "net_flow_dollars": 27312942614.326313,
      "market_cap_delta": 31909713257.899998,
      "lineStyle": {
        "color": "#10b981",
        "opacity": 0.35
      }
    },
    {
      "source": "AI & Cloud Growth",
      "target": "MDB",
      "value": 1527.07,
      "net_flow_dollars": 15270657700.187206,
      "market_cap_delta": 8516133314.411543,
      "lineStyle": {
        "color": "#10b981",
        "opacity": 0.35
      }
    },
    {
      "source": "AI & Cloud Growth",
      "target": "PLTR",
      "value": 1000.02,
      "net_flow_dollars": -10000200033.031507,
      "market_cap_delta": -9914427331.465471,
      "lineStyle": {
        "color": "#ef4444",
        "opacity": 0.35
      }
    },
    {
      "source": "AI & Cloud Growth",
      "target": "ZS",
      "value": 707.43,
      "net_flow_dollars": 7074346089.6851845,
      "market_cap_delta": 4243257639.901015,
      "lineStyle": {
        "color": "#10b981",
        "opacity": 0.35
      }
    },
    {
      "source": "AI & Cloud Growth",
      "target": "U",
      "value": 493.06,
      "net_flow_dollars": 4930564829.855485,
      "market_cap_delta": 3526329485.9531503,
      "lineStyle": {
        "color": "#10b981",
        "opacity": 0.35
      }
    },
    {
      "source": "AI & Cloud Growth",
      "target": "SOFI",
      "value": 320.44,
      "net_flow_dollars": 3204369963.1176233,
      "market_cap_delta": 968470780.3846433,
      "lineStyle": {
        "color": "#10b981",
        "opacity": 0.35
      }
    },
    {
      "source": "AI & Cloud Growth",
      "target": "SMCI",
      "value": 67.99,
      "net_flow_dollars": 679903142.862867,
      "market_cap_delta": 132609414.70745856,
      "lineStyle": {
        "color": "#10b981",
        "opacity": 0.35
      }
    },
    {
      "source": "AI & Cloud Growth",
      "target": "AI",
      "value": 22.19,
      "net_flow_dollars": 221869260.393659,
      "market_cap_delta": 91169570.99999994,
      "lineStyle": {
        "color": "#10b981",
        "opacity": 0.35
      }
    },
    {
      "source": "USA",
      "target": "Financials",
      "value": 1007.07,
      "net_flow_dollars": 10070665969.850672,
      "market_cap_delta": 4373052305.990975,
      "lineStyle": {
        "color": "#10b981",
        "opacity": 0.35
      }
    },
    {
      "source": "Financials",
      "target": "GS",
      "value": 2303.78,
      "net_flow_dollars": 23037811345.98599,
      "market_cap_delta": 65293548826.425766,
      "lineStyle": {
        "color": "#10b981",
        "opacity": 0.35
      }
    },
    {
      "source": "Financials",
      "target": "V",
      "value": 1770.02,
      "net_flow_dollars": 17700228848.101288,
      "market_cap_delta": 79898452334.5848,
      "lineStyle": {
        "color": "#10b981",
        "opacity": 0.35
      }
    },
    {
      "source": "Financials",
      "target": "JPM",
      "value": 1199.73,
      "net_flow_dollars": 11997342399.918358,
      "market_cap_delta": 87888010490.16756,
      "lineStyle": {
        "color": "#10b981",
        "opacity": 0.35
      }
    },
    {
      "source": "Financials",
      "target": "BAC",
      "value": 1187.71,
      "net_flow_dollars": 11877086764.69745,
      "market_cap_delta": 52621215345.7498,
      "lineStyle": {
        "color": "#10b981",
        "opacity": 0.35
      }
    },
    {
      "source": "Financials",
      "target": "MA",
      "value": 492.43,
      "net_flow_dollars": 4924341512.965487,
      "market_cap_delta": 25986564224.084427,
      "lineStyle": {
        "color": "#10b981",
        "opacity": 0.35
      }
    },
    {
      "source": "Financials",
      "target": "WFC",
      "value": 468.58,
      "net_flow_dollars": 4685834308.5299635,
      "market_cap_delta": 19998340211.081432,
      "lineStyle": {
        "color": "#10b981",
        "opacity": 0.35
      }
    },
    {
      "source": "Financials",
      "target": "BLK",
      "value": 71.12,
      "net_flow_dollars": -711203297.3249421,
      "market_cap_delta": -3380449434.0899916,
      "lineStyle": {
        "color": "#ef4444",
        "opacity": 0.35
      }
    },
    {
      "source": "Financials",
      "target": "BX",
      "value": 55.42,
      "net_flow_dollars": -554239877.5929198,
      "market_cap_delta": -1643931917.924102,
      "lineStyle": {
        "color": "#ef4444",
        "opacity": 0.35
      }
    },
    {
      "source": "USA",
      "target": "Healthcare",
      "value": 582.62,
      "net_flow_dollars": 5826220556.431008,
      "market_cap_delta": 1918874480.2227907,
      "lineStyle": {
        "color": "#10b981",
        "opacity": 0.35
      }
    },
    {
      "source": "Healthcare",
      "target": "UNH",
      "value": 4837.27,
      "net_flow_dollars": 48372732735.9041,
      "market_cap_delta": 105925951088.23817,
      "lineStyle": {
        "color": "#10b981",
        "opacity": 0.35
      }
    },
    {
      "source": "Healthcare",
      "target": "LLY",
      "value": 3964.48,
      "net_flow_dollars": 39644761571.63268,
      "market_cap_delta": 201823330170.88916,
      "lineStyle": {
        "color": "#10b981",
        "opacity": 0.35
      }
    },
    {
      "source": "Healthcare",
      "target": "ABBV",
      "value": 990.91,
      "net_flow_dollars": 9909053933.306118,
      "market_cap_delta": 60388982935.239044,
      "lineStyle": {
        "color": "#10b981",
        "opacity": 0.35
      }
    },
    {
      "source": "Healthcare",
      "target": "PFE",
      "value": 520.22,
      "net_flow_dollars": -5202153492.979378,
      "market_cap_delta": -16357406069.529243,
      "lineStyle": {
        "color": "#ef4444",
        "opacity": 0.35
      }
    },
    {
      "source": "Healthcare",
      "target": "JNJ",
      "value": 457.81,
      "net_flow_dollars": 4578088595.938742,
      "market_cap_delta": 33628838715.853687,
      "lineStyle": {
        "color": "#10b981",
        "opacity": 0.35
      }
    },
    {
      "source": "Healthcare",
      "target": "MRK",
      "value": 54.13,
      "net_flow_dollars": 541322793.7554208,
      "market_cap_delta": 3111981777.8223968,
      "lineStyle": {
        "color": "#10b981",
        "opacity": 0.35
      }
    },
    {
      "source": "USA",
      "target": "Industrials",
      "value": 377.26,
      "net_flow_dollars": 3772576086.390991,
      "market_cap_delta": 1075246786.7797859,
      "lineStyle": {
        "color": "#10b981",
        "opacity": 0.35
      }
    },
    {
      "source": "Industrials",
      "target": "CAT",
      "value": 2294.68,
      "net_flow_dollars": 22946841152.651737,
      "market_cap_delta": 67769205916.67358,
      "lineStyle": {
        "color": "#10b981",
        "opacity": 0.35
      }
    },
    {
      "source": "Industrials",
      "target": "GE",
      "value": 1018.51,
      "net_flow_dollars": 10185067250.322407,
      "market_cap_delta": 40940542912.559814,
      "lineStyle": {
        "color": "#10b981",
        "opacity": 0.35
      }
    },
    {
      "source": "Industrials",
      "target": "UNP",
      "value": 532.81,
      "net_flow_dollars": 5328052888.162585,
      "market_cap_delta": 22270175372.15426,
      "lineStyle": {
        "color": "#10b981",
        "opacity": 0.35
      }
    },
    {
      "source": "Industrials",
      "target": "LMT",
      "value": 496.88,
      "net_flow_dollars": -4968814669.259195,
      "market_cap_delta": -20550131566.542843,
      "lineStyle": {
        "color": "#ef4444",
        "opacity": 0.35
      }
    },
    {
      "source": "Industrials",
      "target": "BA",
      "value": 166.37,
      "net_flow_dollars": -1663652594.6937003,
      "market_cap_delta": -3988804502.302854,
      "lineStyle": {
        "color": "#ef4444",
        "opacity": 0.35
      }
    },
    {
      "source": "USA",
      "target": "Consumer",
      "value": 31.23,
      "net_flow_dollars": -312264756.1356452,
      "market_cap_delta": -79367126.79321262,
      "lineStyle": {
        "color": "#ef4444",
        "opacity": 0.35
      }
    },
    {
      "source": "Consumer",
      "target": "TSLA",
      "value": 11252.38,
      "net_flow_dollars": 112523753062.22778,
      "market_cap_delta": 129948000090.36139,
      "lineStyle": {
        "color": "#10b981",
        "opacity": 0.35
      }
    },
    {
      "source": "Consumer",
      "target": "AMZN",
      "value": 921.49,
      "net_flow_dollars": -9214862973.112888,
      "market_cap_delta": -41306230038.41609,
      "lineStyle": {
        "color": "#ef4444",
        "opacity": 0.35
      }
    },
    {
      "source": "Consumer",
      "target": "MCD",
      "value": 589.23,
      "net_flow_dollars": -5892300816.105414,
      "market_cap_delta": -22181992917.98002,
      "lineStyle": {
        "color": "#ef4444",
        "opacity": 0.35
      }
    },
    {
      "source": "Consumer",
      "target": "SBUX",
      "value": 314.53,
      "net_flow_dollars": 3145342601.6477413,
      "market_cap_delta": 9903997173.706057,
      "lineStyle": {
        "color": "#10b981",
        "opacity": 0.35
      }
    },
    {
      "source": "Consumer",
      "target": "NKE",
      "value": 162.48,
      "net_flow_dollars": -1624807781.3313115,
      "market_cap_delta": -1655309373.8381338,
      "lineStyle": {
        "color": "#ef4444",
        "opacity": 0.35
      }
    },
    {
      "source": "Consumer",
      "target": "HD",
      "value": 93.5,
      "net_flow_dollars": -934997974.9309303,
      "market_cap_delta": -4501974516.129281,
      "lineStyle": {
        "color": "#ef4444",
        "opacity": 0.35
      }
    },
    {
      "source": "Equities",
      "target": "Emerging Markets",
      "value": 52.4,
      "net_flow_dollars": 523992449.7010941,
      "market_cap_delta": 1503208430.4875827,
      "lineStyle": {
        "color": "#10b981",
        "opacity": 0.35
      }
    },
    {
      "source": "Equities",
      "target": "Asia-Pacific",
      "value": 22.8,
      "net_flow_dollars": 228043794.47678545,
      "market_cap_delta": 118743536.24719243,
      "lineStyle": {
        "color": "#10b981",
        "opacity": 0.35
      }
    },
    {
      "source": "Equities",
      "target": "Europe",
      "value": 5.35,
      "net_flow_dollars": 53511594.07925638,
      "market_cap_delta": 93089826.48050652,
      "lineStyle": {
        "color": "#10b981",
        "opacity": 0.35
      }
    },
    {
      "source": "Global Liquidity",
      "target": "Crypto",
      "value": 1487.98,
      "net_flow_dollars": -14879817998.99288,
      "market_cap_delta": -6030001525.878909,
      "lineStyle": {
        "color": "#ef4444",
        "opacity": 0.35
      }
    },
    {
      "source": "Crypto",
      "target": "MicroStrategy",
      "value": 4902.35,
      "net_flow_dollars": -49023526138.828125,
      "market_cap_delta": -14170573651.14963,
      "lineStyle": {
        "color": "#ef4444",
        "opacity": 0.35
      }
    },
    {
      "source": "Crypto",
      "target": "Bitcoin",
      "value": 1487.98,
      "net_flow_dollars": -14879817998.99288,
      "market_cap_delta": -6030001525.878909,
      "lineStyle": {
        "color": "#ef4444",
        "opacity": 0.35
      }
    },
    {
      "source": "Crypto",
      "target": "Coinbase",
      "value": 1246.4,
      "net_flow_dollars": -12463999796.52433,
      "market_cap_delta": -5777538621.159362,
      "lineStyle": {
        "color": "#ef4444",
        "opacity": 0.35
      }
    },
    {
      "source": "Crypto",
      "target": "Ethereum",
      "value": 482.2,
      "net_flow_dollars": -4822043792.745469,
      "market_cap_delta": -3429999580.3832994,
      "lineStyle": {
        "color": "#ef4444",
        "opacity": 0.35
      }
    },
    {
      "source": "Global Liquidity",
      "target": "Fixed Income",
      "value": 374.12,
      "net_flow_dollars": -3741187452.428053,
      "market_cap_delta": -327454667.38891536,
      "lineStyle": {
        "color": "#ef4444",
        "opacity": 0.35
      }
    },
    {
      "source": "Global Liquidity",
      "target": "Real Estate",
      "value": 60.58,
      "net_flow_dollars": 605845657.8169019,
      "market_cap_delta": 1227151344.1232817,
      "lineStyle": {
        "color": "#10b981",
        "opacity": 0.35
      }
    },
    {
      "source": "Global Liquidity",
      "target": "Commodities",
      "value": 1.81,
      "net_flow_dollars": -18133265.34891267,
      "market_cap_delta": -27849983.00170897,
      "lineStyle": {
        "color": "#ef4444",
        "opacity": 0.35
      }
    },
    {
      "source": "Commodities",
      "target": "Gold",
      "value": 2658.79,
      "net_flow_dollars": -26587933349.54409,
      "market_cap_delta": -18543770411.25488,
      "lineStyle": {
        "color": "#ef4444",
        "opacity": 0.35
      }
    },
    {
      "source": "Commodities",
      "target": "Silver",
      "value": 2206.55,
      "net_flow_dollars": -22065489976.746418,
      "market_cap_delta": -6388528575.426409,
      "lineStyle": {
        "color": "#ef4444",
        "opacity": 0.35
      }
    },
    {
      "source": "Commodities",
      "target": "Crude Oil",
      "value": 209.86,
      "net_flow_dollars": -2098605315.7189496,
      "market_cap_delta": -447816436.1572259,
      "lineStyle": {
        "color": "#ef4444",
        "opacity": 0.35
      }
    },
    {
      "source": "Commodities",
      "target": "Copper",
      "value": 6.33,
      "net_flow_dollars": 63264708.54193219,
      "market_cap_delta": 1540098419.1894553,
      "lineStyle": {
        "color": "#10b981",
        "opacity": 0.35
      }
    }
  ],
  "regime_summary": {
    "title": "Bull Market (Buying)",
    "liquidity": "Flowing IN (Positive)",
    "inflow": "MU / AMD / INTC / SPY / AAPL",
    "outflow": "MSTR / GLD / SLV / MSFT / IBIT",
    "health": "Optimal"
  },
  "discovery_radar": [
    {
      "symbol": "CALM",
      "name": "Cal-Maine Foods, Inc.",
      "sector": "Consumer Defensive",
      "rev_growth": -0.53,
      "earn_growth": -0.898,
      "dollar_volume": 2817273370.837118,
      "price_change": 0.09753838413414212
    },
    {
      "symbol": "CPRX",
      "name": "Catalyst Pharmaceuticals, Inc.",
      "sector": "Healthcare",
      "rev_growth": 0.056,
      "earn_growth": 0.111,
      "dollar_volume": 3618165012.2451644,
      "price_change": 0.20236730703009403
    },
    {
      "symbol": "NSP",
      "name": "Insperity, Inc.",
      "sector": "Industrials",
      "rev_growth": 0.017,
      "earn_growth": -0.353,
      "dollar_volume": 1218790126.639848,
      "price_change": 0.7227255809821267
    },
    {
      "symbol": "LAD",
      "name": "Lithia Motors, Inc.",
      "sector": "Consumer Cyclical",
      "rev_growth": 0.01,
      "earn_growth": -0.461,
      "dollar_volume": 4160927294.28872,
      "price_change": 0.11966782596351774
    },
    {
      "symbol": "CAKE",
      "name": "The Cheesecake Factory Incorpor",
      "sector": "Consumer Cyclical",
      "rev_growth": 0.056,
      "earn_growth": 0.522,
      "dollar_volume": 4565994380.901751,
      "price_change": 0.33708788217612434
    },
    {
      "symbol": "NTNX",
      "name": "Nutanix, Inc.",
      "sector": "Technology",
      "rev_growth": 0.1,
      "earn_growth": 0.172,
      "dollar_volume": 8719795393.909313,
      "price_change": 0.5059516444790148
    },
    {
      "symbol": "SN",
      "name": "SharkNinja, Inc.",
      "sector": "Consumer Cyclical",
      "rev_growth": 0.156,
      "earn_growth": 0.024,
      "dollar_volume": 11253357255.49901,
      "price_change": 0.2849181223557538
    },
    {
      "symbol": "JXN",
      "name": "Jackson Financial Inc.",
      "sector": "Financial Services",
      "rev_growth": -0.226,
      "earn_growth": 0,
      "dollar_volume": 2860250613.535156,
      "price_change": 0.1509613379872959
    },
    {
      "symbol": "WDFC",
      "name": "WD-40 Company",
      "sector": "Basic Materials",
      "rev_growth": 0.243,
      "earn_growth": 0.455,
      "dollar_volume": 1995577008.127367,
      "price_change": 0.20659763123622688
    },
    {
      "symbol": "TFIN",
      "name": "Triumph Financial, Inc.",
      "sector": "Financial Services",
      "rev_growth": 0.062,
      "earn_growth": 0,
      "dollar_volume": 908341326.6006604,
      "price_change": 0.2790792092367983
    },
    {
      "symbol": "SAH",
      "name": "Sonic Automotive, Inc.",
      "sector": "Consumer Cyclical",
      "rev_growth": 0.01,
      "earn_growth": -0.123,
      "dollar_volume": 1001630715.734899,
      "price_change": 0.32111973310345054
    },
    {
      "symbol": "PSMT",
      "name": "PriceSmart, Inc.",
      "sector": "Consumer Defensive",
      "rev_growth": 0.125,
      "earn_growth": 0.123,
      "dollar_volume": 2186715223.3025255,
      "price_change": 0.23640890934444192
    },
    {
      "symbol": "TBBK",
      "name": "The Bancorp, Inc.",
      "sector": "Financial Services",
      "rev_growth": 0.041,
      "earn_growth": 0.185,
      "dollar_volume": 1177936767.3198812,
      "price_change": 0.11859560453369097
    },
    {
      "symbol": "PENG",
      "name": "Penguin Solutions, Inc.",
      "sector": "Technology",
      "rev_growth": 0.476,
      "earn_growth": 0,
      "dollar_volume": 10233636980.065044,
      "price_change": 1.8036547671209784
    },
    {
      "symbol": "SMPL",
      "name": "The Simply Good Foods Company",
      "sector": "Consumer Defensive",
      "rev_growth": -0.063,
      "earn_growth": 0,
      "dollar_volume": 1491975577.999037,
      "price_change": 0.11237928676856407
    },
    {
      "symbol": "PTGX",
      "name": "Protagonist Therapeutics, Inc.",
      "sector": "Healthcare",
      "rev_growth": 0.99,
      "earn_growth": 0,
      "dollar_volume": 3270749806.5397015,
      "price_change": 0.24512986430145567
    },
    {
      "symbol": "GSHD",
      "name": "Goosehead Insurance, Inc.",
      "sector": "Financial Services",
      "rev_growth": 0.233,
      "earn_growth": 1.119,
      "dollar_volume": 1104436172.81172,
      "price_change": 0.2953086193696952
    },
    {
      "symbol": "ADUS",
      "name": "Addus HomeCare Corporation",
      "sector": "Healthcare",
      "rev_growth": 0.077,
      "earn_growth": 0.172,
      "dollar_volume": 1156651550.1138234,
      "price_change": 0.15284783178090303
    },
    {
      "symbol": "PATH",
      "name": "UiPath, Inc.",
      "sector": "Technology",
      "rev_growth": 0.173,
      "earn_growth": 0,
      "dollar_volume": 27744575585.79077,
      "price_change": 0.16566869313131555
    },
    {
      "symbol": "LZ",
      "name": "LegalZoom.com, Inc.",
      "sector": "Industrials",
      "rev_growth": 0.129,
      "earn_growth": -0.782,
      "dollar_volume": 841516906.3059468,
      "price_change": 0.23710481577030637
    },
    {
      "symbol": "CBSH",
      "name": "Commerce Bancshares, Inc.",
      "sector": "Financial Services",
      "rev_growth": 0.173,
      "earn_growth": 0.031,
      "dollar_volume": 3291783393.298233,
      "price_change": 0.15311757353411573
    },
    {
      "symbol": "PBF",
      "name": "PBF Energy Inc.",
      "sector": "Energy",
      "rev_growth": 0.119,
      "earn_growth": 0,
      "dollar_volume": 6140635106.937688,
      "price_change": 0.5170687767514458
    },
    {
      "symbol": "OGN",
      "name": "Organon & Co.",
      "sector": "Healthcare",
      "rev_growth": -0.035,
      "earn_growth": 0.667,
      "dollar_volume": 5278562470.328709,
      "price_change": 0.5517241379310346
    },
    {
      "symbol": "MANH",
      "name": "Manhattan Associates, Inc.",
      "sector": "Technology",
      "rev_growth": 0.074,
      "earn_growth": -0.035,
      "dollar_volume": 4765023701.981644,
      "price_change": 0.2230173746744792
    },
    {
      "symbol": "IPAR",
      "name": "Interparfums, Inc.",
      "sector": "Consumer Defensive",
      "rev_growth": 0.018,
      "earn_growth": 0.023,
      "dollar_volume": 1280109415.8482006,
      "price_change": 0.22534330814915596
    },
    {
      "symbol": "CXW",
      "name": "CoreCivic, Inc.",
      "sector": "Industrials",
      "rev_growth": 0.258,
      "earn_growth": 0.657,
      "dollar_volume": 1371320958.5496323,
      "price_change": 0.5979899738665512
    },
    {
      "symbol": "ECPG",
      "name": "Encore Capital Group Inc",
      "sector": "Financial Services",
      "rev_growth": 0.21,
      "earn_growth": 1.0,
      "dollar_volume": 1384431293.6011682,
      "price_change": 0.13536570066491038
    },
    {
      "symbol": "UNM",
      "name": "Unum Group",
      "sector": "Financial Services",
      "rev_growth": 0.085,
      "earn_growth": 0.33,
      "dollar_volume": 5409376458.316243,
      "price_change": 0.15761640655230233
    },
    {
      "symbol": "RDNT",
      "name": "RadNet, Inc.",
      "sector": "Healthcare",
      "rev_growth": 0.221,
      "earn_growth": 0,
      "dollar_volume": 2460689718.8551245,
      "price_change": 0.07894736313753845
    },
    {
      "symbol": "ANIP",
      "name": "ANI Pharmaceuticals, Inc.",
      "sector": "Healthcare",
      "rev_growth": 0.205,
      "earn_growth": 0.861,
      "dollar_volume": 1333194441.3368247,
      "price_change": 0.03780814918891293
    },
    {
      "symbol": "HAYW",
      "name": "Hayward Holdings, Inc.",
      "sector": "Industrials",
      "rev_growth": 0.115,
      "earn_growth": 0.791,
      "dollar_volume": 1961148948.409109,
      "price_change": 0.05727759975628712
    },
    {
      "symbol": "LNN",
      "name": "Lindsay Corporation",
      "sector": "Industrials",
      "rev_growth": -0.051,
      "earn_growth": -0.14,
      "dollar_volume": 1063918094.6839012,
      "price_change": 0.030055098149480985
    },
    {
      "symbol": "MSM",
      "name": "MSC Industrial Direct Company, ",
      "sector": "Industrials",
      "rev_growth": 0.078,
      "earn_growth": 0.411,
      "dollar_volume": 4046146757.194265,
      "price_change": 0.2921278151621473
    },
    {
      "symbol": "PTCT",
      "name": "PTC Therapeutics, Inc.",
      "sector": "Healthcare",
      "rev_growth": -0.768,
      "earn_growth": 0,
      "dollar_volume": 5939422031.1786175,
      "price_change": 0.10252024033121525
    },
    {
      "symbol": "WRLD",
      "name": "World Acceptance Corporation",
      "sector": "Financial Services",
      "rev_growth": 0.073,
      "earn_growth": -0.054,
      "dollar_volume": 1391960687.7095985,
      "price_change": 0.4273967026099149
    },
    {
      "symbol": "EGBN",
      "name": "Eagle Bancorp, Inc.",
      "sector": "Financial Services",
      "rev_growth": 0.353,
      "earn_growth": 7.676,
      "dollar_volume": 345700166.27927065,
      "price_change": 0.017662530015259498
    },
    {
      "symbol": "DAVE",
      "name": "Dave Inc.",
      "sector": "Technology",
      "rev_growth": 0.467,
      "earn_growth": 1.041,
      "dollar_volume": 9237328179.48241,
      "price_change": 0.873666797569412
    },
    {
      "symbol": "CART",
      "name": "Maplebear Inc.",
      "sector": "Consumer Cyclical",
      "rev_growth": 0.136,
      "earn_growth": 0.535,
      "dollar_volume": 8808078209.633795,
      "price_change": 0.21123200273501727
    },
    {
      "symbol": "DRH",
      "name": "Diamondrock Hospitality Company",
      "sector": "Real Estate",
      "rev_growth": 0.013,
      "earn_growth": 0.75,
      "dollar_volume": 980593240.9253286,
      "price_change": 0.1436118859722566
    },
    {
      "symbol": "CON",
      "name": "Concentra Group Holdings Parent",
      "sector": "Healthcare",
      "rev_growth": 0.137,
      "earn_growth": 0.294,
      "dollar_volume": 1085777855.3427324,
      "price_change": 0.35868131197415865
    }
  ],
  "last_updated": "2026-07-14 14:21:16 UTC"
}